<?xml version="1.0" encoding="UTF-8"?>
<!--
	Created by ZK Studio
-->
<zk>
 <!-- Turn on if you want to debug JavaScript.
		Once turned on, the uncompressed JavaScript files will be loaded.
	-->
 <client-config>
  <debug-js>true</debug-js>
 </client-config>
 <session-config>
  <!-- Turn on the following if you want a different timeout
			Note: The unit is seconds (while that of web.xml is minute)
		-->
  <session-timeout>1800</session-timeout>
  <!-- Turn on the following if you want to reset the session-timeout
		counter when receiving onTimer, like any other request
		In other words, the session is never timeoout if the desktop has
		a timer.
		<timer-keep-alive>true</timer-keep-alive>
		-->
 </session-config>
 <library-property>
  <name>org.zkoss.zul.include.mode</name>
  <value>auto</value>
 </library-property>
 <!--
    <library-property>
        <name>org.zkoss.zul.theme.fontFamilyC</name>
        <value>Courier New</value>
    </library-property>
    <library-property>
        <name>org.zkoss.zul.theme.fontFamilyT</name>
        <value>Courier New</value>
    </library-property>
    -->
 <device-config>
  <device-type>ajax</device-type>
  <timeout-uri>/index.zul</timeout-uri>
  <!-- An empty URL can cause the browser to reload the same URL -->
 </device-config>
 <!-- Uncomment if you want to embed JavaScript codes and any other
	tags to be generated inside HTML HEAD.
	-->
 <device-config>
  <device-type>ajax</device-type>
  <embed>
   <![CDATA[
                <script type="text/javascript">
                </script>
            ]]>
  </embed>
 </device-config>
 <!-- Optional -->
 <!-- the following listener is used to see # of sessions, desktops...
	<listener>
		<description>[Optional] Mointor the statistic</description>
		<listener-class>org.zkoss.zk.ui.util.Statistic</listener-class>
	</listener>
	-->
</zk>
